ocnn/__init__.py
ocnn/dataset.py
ocnn/utils.py
ocnn/models/__init__.py
ocnn/models/autoencoder.py
ocnn/models/hrnet.py
ocnn/models/image2shape.py
ocnn/models/lenet.py
ocnn/models/ounet.py
ocnn/models/resnet.py
ocnn/models/segnet.py
ocnn/models/unet.py
ocnn/modules/__init__.py
ocnn/modules/modules.py
ocnn/modules/resblocks.py
ocnn/nn/__init__.py
ocnn/nn/octree2col.py
ocnn/nn/octree2vox.py
ocnn/nn/octree_align.py
ocnn/nn/octree_conv.py
ocnn/nn/octree_drop.py
ocnn/nn/octree_dwconv.py
ocnn/nn/octree_gconv.py
ocnn/nn/octree_interp.py
ocnn/nn/octree_norm.py
ocnn/nn/octree_pad.py
ocnn/nn/octree_pool.py
ocnn/octree/__init__.py
ocnn/octree/octree.py
ocnn/octree/points.py
ocnn/octree/shuffled_key.py
ocnn-2.2.8.dist-info/licenses/LICENSE
ocnn-2.2.8.dist-info/METADATA
ocnn-2.2.8.dist-info/WHEEL
ocnn-2.2.8.dist-info/top_level.txt
ocnn-2.2.8.dist-info/RECORD
