Metadata-Version: 2.4
Name: ocnn
Version: 2.2.8
Summary: Octree-based Sparse Convolutional Neural Networks
Home-page: https://github.com/octree-nn/ocnn-pytorch
Author: Peng-Shuai Wang
Author-email: wangps@hotmail.com
License: MIT
Classifier: Programming Language :: Python :: 3
Classifier: Operating System :: OS Independent
Requires-Python: >=3.6
License-File: LICENSE
Requires-Dist: torch
Requires-Dist: torchvision
Requires-Dist: numpy
Requires-Dist: packaging
Dynamic: author
Dynamic: author-email
Dynamic: classifier
Dynamic: description
Dynamic: description-content-type
Dynamic: home-page
Dynamic: license
Dynamic: license-file
Dynamic: requires-dist
Dynamic: requires-python
Dynamic: summary
